{
  "apidoc": {
    "version": "0.11.23"
  },
  "name": "harmonization-internal",
  "organization": {
    "key": "flow"
  },
  "application": {
    "key": "harmonization-internal"
  },
  "namespace": "io.flow.harmonization.internal.v0",
  "version": "0.0.53",
  "info": {
    "license": {
      "name": "MIT",
      "url": "http://opensource.org/licenses/MIT"
    },
    "contact": {
      "email": "tech@flow.io"
    }
  },
  "headers": [],
  "imports": [
    {
      "uri": "http://www.apidoc.me/flow/common/0.0.12/service.json",
      "namespace": "io.flow.common.v0",
      "organization": {
        "key": "flow"
      },
      "application": {
        "key": "common"
      },
      "version": "0.0.12",
      "enums": [
        "calendar",
        "capability",
        "change_type",
        "exception_type",
        "holiday_calendar",
        "schedule_exception_status",
        "unit_of_measurement",
        "unit_of_time",
        "value_added_service",
        "visibility"
      ],
      "unions": [
        "expandable_organization",
        "expandable_user"
      ],
      "models": [
        "address",
        "contact",
        "datetime_range",
        "dimension",
        "error",
        "exception",
        "healthcheck",
        "location",
        "measurement",
        "name",
        "organization",
        "organization_reference",
        "organization_summary",
        "price",
        "schedule",
        "user",
        "user_reference",
        "user_summary"
      ]
    }
  ],
  "enums": [
    {
      "name": "duty_type",
      "plural": "duty_types",
      "values": [
        {
          "name": "General",
          "attributes": []
        }
      ],
      "attributes": []
    },
    {
      "name": "status",
      "plural": "statuses",
      "values": [
        {
          "name": "queued",
          "attributes": [],
          "description": "The classification request is pending processing"
        },
        {
          "name": "processing",
          "attributes": [],
          "description": "The classification request is actively being processed"
        },
        {
          "name": "completed",
          "attributes": [],
          "description": "The classification request has been successfully processed and classification results are available"
        },
        {
          "name": "failed",
          "attributes": [],
          "description": "The classification request was unable to be processed due to an error. No further attempts to classify this record will be made"
        }
      ],
      "attributes": [],
      "description": "Describes the status of a classification request. The status is a finite state machine. Initial status is 'Queued'. Valid transitions are 'Queued' to 'Processing', 'Processing' to 'Queued', 'Completed' or 'Failed'. Note that we only report failure after multiple attempts to process the request have failed."
    }
  ],
  "unions": [
    {
      "name": "expandable_classification",
      "plural": "expandable_classifications",
      "types": [
        {
          "type": "classification",
          "attributes": []
        },
        {
          "type": "classification_reference",
          "attributes": []
        }
      ],
      "attributes": [],
      "discriminator": "discriminator"
    },
    {
      "name": "result",
      "plural": "results",
      "types": [
        {
          "type": "threece_result",
          "attributes": []
        },
        {
          "type": "flow_result",
          "attributes": []
        }
      ],
      "attributes": [],
      "discriminator": "discriminator",
      "description": "Result is used to summarize the recommendations for classification codes from a specific strategy, storing information specific to each of the algorithms we run to classify the items"
    },
    {
      "name": "task_data",
      "plural": "task_data",
      "types": [
        {
          "type": "task_summarize_code",
          "attributes": []
        }
      ],
      "attributes": [],
      "discriminator": "discriminator"
    },
    {
      "name": "tax",
      "plural": "taxes",
      "types": [
        {
          "type": "tax_simple",
          "attributes": []
        },
        {
          "type": "tax_canada",
          "attributes": []
        }
      ],
      "attributes": [],
      "discriminator": "discriminator"
    }
  ],
  "models": [
    {
      "name": "classification",
      "plural": "classifications",
      "fields": [
        {
          "name": "id",
          "type": "string",
          "required": true,
          "attributes": []
        },
        {
          "name": "item",
          "type": "item",
          "required": true,
          "attributes": [],
          "description": "The item that we are classifying."
        },
        {
          "name": "status",
          "type": "status",
          "required": true,
          "attributes": [],
          "description": "Current status of the request"
        },
        {
          "name": "hs6",
          "type": "string",
          "required": false,
          "attributes": [],
          "description": "The HS6 code - this will only be present once the status is completed, but it is not guaranteed that we will have been able to resolve a harmonization code for this item. In these cases, there will be no hs6 code."
        },
        {
          "name": "results",
          "type": "[result]",
          "required": false,
          "attributes": [],
          "description": "Once completed, results for this classification request will be available here"
        }
      ],
      "attributes": [],
      "description": "The actual classification record. Users request classification of their items and this model holds all of the data, including the results once available. Classification proceeds in near real-time for cases where there is sufficient data to classify the item automatically."
    },
    {
      "name": "classification_form",
      "plural": "classification_forms",
      "fields": [
        {
          "name": "item",
          "type": "item_form",
          "required": true,
          "attributes": [],
          "description": "The data we are actually classifying"
        }
      ],
      "attributes": [],
      "description": "Defines the data needed to request a classification. Only the item description is required, though we recommend also providing an item number to facilitate lookup of results"
    },
    {
      "name": "classification_reference",
      "plural": "classification_references",
      "fields": [
        {
          "name": "id",
          "type": "string",
          "required": true,
          "attributes": []
        }
      ],
      "attributes": []
    },
    {
      "name": "detail",
      "plural": "details",
      "fields": [
        {
          "name": "id",
          "type": "string",
          "required": true,
          "attributes": []
        },
        {
          "name": "classification",
          "type": "expandable_classification",
          "required": true,
          "attributes": [],
          "description": "The classification record for which we are requesting detailed information."
        },
        {
          "name": "country_of_origin",
          "type": "string",
          "required": true,
          "attributes": [],
          "description": "The ISO 3166-3 code for the country of origin. Case insensitive. See https://reference.api.flow.io/countries",
          "example": "USA"
        },
        {
          "name": "destination",
          "type": "string",
          "required": true,
          "attributes": [],
          "description": "The ISO 3166-3 code for the destination country. Case insensitive. See https://reference.api.flow.io/countries",
          "example": "CAN"
        },
        {
          "name": "status",
          "type": "status",
          "required": true,
          "attributes": [],
          "description": "Current status of the detailed classification"
        },
        {
          "name": "code",
          "type": "string",
          "required": false,
          "attributes": [],
          "description": "Once ready, this is the detailed harmonization code (e.g. hs10 or hs12) for this particular trade lane"
        },
        {
          "name": "duties",
          "type": "[duty]",
          "required": false,
          "attributes": [],
          "description": "Once ready, details on all duties that are applied"
        },
        {
          "name": "taxes",
          "type": "[tax]",
          "required": false,
          "attributes": [],
          "description": "Once ready, details on all taxes that are applied. Note the data is unstructured as the format of the tax information varies by country"
        }
      ],
      "attributes": [],
      "description": "The detailed classification of a given item from one country to another country."
    },
    {
      "name": "detail_form",
      "plural": "detail_forms",
      "fields": [
        {
          "name": "classification_id",
          "type": "string",
          "required": true,
          "attributes": [],
          "description": "The classification record for which we are requesting detailed information. We will only pursue detailed information once this classification has successfully resulted in an hs6 code"
        },
        {
          "name": "country_of_origin",
          "type": "string",
          "required": true,
          "attributes": [],
          "description": "The ISO 3166-3 code for the country of origin. Case insensitive. See https://reference.api.flow.io/countries",
          "example": "USA"
        },
        {
          "name": "destination",
          "type": "string",
          "required": true,
          "attributes": [],
          "description": "The ISO 3166-3 code for the destination country. Case insensitive. See https://reference.api.flow.io/countries",
          "example": "CAN"
        }
      ],
      "attributes": [],
      "description": "The detail form defines the data required to request detailed classification of a single trade lane for a single classification"
    },
    {
      "name": "duty",
      "plural": "duties",
      "fields": [
        {
          "name": "name",
          "type": "string",
          "required": true,
          "attributes": [],
          "example": "ERGA OMNES"
        },
        {
          "name": "rate",
          "type": "decimal",
          "required": true,
          "attributes": [],
          "example": ".12 or .165"
        }
      ],
      "attributes": []
    },
    {
      "name": "flow_result",
      "plural": "flow_results",
      "fields": [
        {
          "name": "code",
          "type": "string",
          "required": true,
          "attributes": []
        }
      ],
      "attributes": []
    },
    {
      "name": "item",
      "plural": "items",
      "fields": [
        {
          "name": "number",
          "type": "string",
          "required": true,
          "attributes": [],
          "description": "Unique external identifier for this item. While not required, providing your item number will enable you to lookup classification results by your item number."
        },
        {
          "name": "description",
          "type": "string",
          "required": false,
          "attributes": [],
          "description": "Description of the item that is being classified.",
          "example": "woven blazer 25% cotton 75% wool"
        },
        {
          "name": "categories",
          "type": "[string]",
          "required": true,
          "attributes": [],
          "default": "[]"
        }
      ],
      "attributes": [],
      "description": "Defines the data available about each item we are classifying"
    },
    {
      "name": "item_form",
      "plural": "item_forms",
      "fields": [
        {
          "name": "number",
          "type": "string",
          "required": true,
          "attributes": [],
          "description": "Unique external identifier for this item. While not required, providing your item number will enable you to lookup classification results by your item number."
        },
        {
          "name": "description",
          "type": "string",
          "required": false,
          "attributes": [],
          "description": "Description of the item that is being classified.",
          "example": "woven blazer 25% cotton 75% wool"
        },
        {
          "name": "categories",
          "type": "[string]",
          "required": false,
          "attributes": []
        }
      ],
      "attributes": [],
      "description": "Defines the information that may be provided to request classification. Note that only the description is required but additional data may aid classification."
    },
    {
      "name": "lane",
      "plural": "lanes",
      "fields": [
        {
          "name": "id",
          "type": "string",
          "required": true,
          "attributes": []
        },
        {
          "name": "country_of_origin",
          "type": "string",
          "required": true,
          "attributes": [],
          "description": "The ISO 3166-3 code for the country of origin. Case insensitive. See https://reference.api.flow.io/countries",
          "example": "USA"
        },
        {
          "name": "destination",
          "type": "string",
          "required": true,
          "attributes": [],
          "description": "The ISO 3166-3 code for the destination country. Case insensitive. See https://reference.api.flow.io/countries",
          "example": "CAN"
        }
      ],
      "attributes": [],
      "description": "An organization can create 1 or more lanes which represent country pairs - e.g. country of origin to destination. This will enable an automated workflow such that whenever a classification request is created, we will automatically create detail records for each of these lanes."
    },
    {
      "name": "lane_form",
      "plural": "lane_forms",
      "fields": [
        {
          "name": "country_of_origin",
          "type": "string",
          "required": true,
          "attributes": [],
          "description": "The ISO 3166 2 or 3 character code for the country of origin. Case insensitive. See https://reference.api.flow.io/countries",
          "example": "USA"
        },
        {
          "name": "destination",
          "type": "string",
          "required": true,
          "attributes": [],
          "description": "The ISO 3166 2 or 3 character code for the destination country. Case insensitive. See https://reference.api.flow.io/countries",
          "example": "CAN"
        }
      ],
      "attributes": []
    },
    {
      "name": "rate",
      "plural": "rates",
      "fields": [
        {
          "name": "id",
          "type": "string",
          "required": true,
          "attributes": []
        },
        {
          "name": "country_of_origin",
          "type": "string",
          "required": true,
          "attributes": [],
          "description": "The ISO 3166-3 code for the country of origin. Case insensitive. See https://reference.api.flow.io/countries",
          "example": "USA"
        },
        {
          "name": "destination",
          "type": "string",
          "required": true,
          "attributes": [],
          "description": "The ISO 3166-3 code for the destination country. Case insensitive. See https://reference.api.flow.io/countries",
          "example": "CAN"
        },
        {
          "name": "code",
          "type": "string",
          "required": true,
          "attributes": [],
          "description": "The detailed harmonization code (e.g. hs10 or hs12) for this particular trade lane"
        },
        {
          "name": "rate",
          "type": "double",
          "required": true,
          "attributes": [],
          "description": "The actual rate, expressed as a number >= 0",
          "minimum": 0,
          "example": ".15"
        }
      ],
      "attributes": [],
      "description": "Duty rates based on the detail harmonization code between two countries."
    },
    {
      "name": "task_summarize_code",
      "plural": "task_summarize_codes",
      "fields": [
        {
          "name": "organization",
          "type": "string",
          "required": true,
          "attributes": []
        },
        {
          "name": "classification_id",
          "type": "string",
          "required": true,
          "attributes": []
        },
        {
          "name": "country_of_origin",
          "type": "string",
          "required": true,
          "attributes": [],
          "description": "The ISO 3166-3 code for the country of origin"
        },
        {
          "name": "destination",
          "type": "string",
          "required": true,
          "attributes": [],
          "description": "The ISO 3166-3 code for the destination country"
        },
        {
          "name": "code",
          "type": "string",
          "required": true,
          "attributes": []
        }
      ],
      "attributes": [],
      "description": "Request to summarize data for an HS code. Triggered when a new HS code is assigned (with duty information). This indicates that we need to recalculate statistics for the associated hs codes - eg compute min, avg, max duty rates for this hs4, 5, 6 globally and for the organization"
    },
    {
      "name": "tax_canada",
      "plural": "tax_canadas",
      "fields": [
        {
          "name": "province",
          "type": "string",
          "required": true,
          "attributes": []
        },
        {
          "name": "application",
          "type": "string",
          "required": true,
          "attributes": []
        },
        {
          "name": "normalRate",
          "type": "tax_canada_rate",
          "required": true,
          "attributes": []
        },
        {
          "name": "exemption",
          "type": "tax_canada_rate",
          "required": true,
          "attributes": []
        }
      ],
      "attributes": []
    },
    {
      "name": "tax_canada_rate",
      "plural": "tax_canada_rates",
      "fields": [
        {
          "name": "federal",
          "type": "decimal",
          "required": true,
          "attributes": []
        },
        {
          "name": "provincial",
          "type": "decimal",
          "required": true,
          "attributes": []
        }
      ],
      "attributes": []
    },
    {
      "name": "tax_simple",
      "plural": "tax_simples",
      "fields": [
        {
          "name": "name",
          "type": "string",
          "required": true,
          "attributes": []
        },
        {
          "name": "rates",
          "type": "[decimal]",
          "required": true,
          "attributes": []
        }
      ],
      "attributes": []
    },
    {
      "name": "threece_result",
      "plural": "threece_results",
      "fields": [
        {
          "name": "code",
          "type": "string",
          "required": true,
          "attributes": []
        },
        {
          "name": "product_id",
          "type": "string",
          "required": true,
          "attributes": [],
          "description": "The 3CE assigned product Id for this classification record."
        }
      ],
      "attributes": []
    }
  ],
  "resources": [
    {
      "type": "classification",
      "plural": "classifications",
      "operations": [
        {
          "method": "GET",
          "path": "/:organization/harmonization/classifications",
          "parameters": [
            {
              "name": "organization",
              "type": "string",
              "location": "Path",
              "required": true
            },
            {
              "name": "id",
              "type": "[string]",
              "location": "Query",
              "required": false,
              "maximum": 100
            },
            {
              "name": "number",
              "type": "[string]",
              "location": "Query",
              "required": false,
              "maximum": 100
            },
            {
              "name": "status",
              "type": "status",
              "location": "Query",
              "required": false
            },
            {
              "name": "limit",
              "type": "long",
              "location": "Query",
              "required": true,
              "default": "25",
              "minimum": 1,
              "maximum": 100
            },
            {
              "name": "offset",
              "type": "long",
              "location": "Query",
              "required": true,
              "default": "0",
              "minimum": 0
            },
            {
              "name": "sort",
              "type": "string",
              "location": "Query",
              "required": true,
              "default": "-created_at"
            }
          ],
          "responses": [
            {
              "code": {
                "integer": {
                  "value": 200
                }
              },
              "type": "[classification]"
            },
            {
              "code": {
                "integer": {
                  "value": 401
                }
              },
              "type": "unit"
            }
          ],
          "attributes": [],
          "description": "Search classifications requests. Always paginated."
        },
        {
          "method": "GET",
          "path": "/:organization/harmonization/classifications/:id",
          "parameters": [
            {
              "name": "organization",
              "type": "string",
              "location": "Path",
              "required": true
            },
            {
              "name": "id",
              "type": "string",
              "location": "Path",
              "required": true
            }
          ],
          "responses": [
            {
              "code": {
                "integer": {
                  "value": 200
                }
              },
              "type": "classification"
            },
            {
              "code": {
                "integer": {
                  "value": 401
                }
              },
              "type": "unit"
            },
            {
              "code": {
                "integer": {
                  "value": 404
                }
              },
              "type": "unit"
            }
          ],
          "attributes": [],
          "description": "Returns information about a specific classification request."
        },
        {
          "method": "POST",
          "path": "/:organization/harmonization/classifications",
          "parameters": [
            {
              "name": "organization",
              "type": "string",
              "location": "Path",
              "required": true
            }
          ],
          "responses": [
            {
              "code": {
                "integer": {
                  "value": 201
                }
              },
              "type": "classification"
            },
            {
              "code": {
                "integer": {
                  "value": 401
                }
              },
              "type": "unit"
            },
            {
              "code": {
                "integer": {
                  "value": 422
                }
              },
              "type": "[io.flow.common.v0.models.error]"
            }
          ],
          "attributes": [],
          "description": "Create a classification request, which will be processed asynchronously. You can check for results by querying with GET using the id provided in the response.",
          "body": {
            "type": "classification_form",
            "attributes": []
          }
        },
        {
          "method": "DELETE",
          "path": "/:organization/harmonization/classifications/:id",
          "parameters": [
            {
              "name": "organization",
              "type": "string",
              "location": "Path",
              "required": true
            },
            {
              "name": "id",
              "type": "string",
              "location": "Path",
              "required": true
            }
          ],
          "responses": [
            {
              "code": {
                "integer": {
                  "value": 204
                }
              },
              "type": "unit"
            },
            {
              "code": {
                "integer": {
                  "value": 401
                }
              },
              "type": "unit"
            },
            {
              "code": {
                "integer": {
                  "value": 404
                }
              },
              "type": "unit"
            }
          ],
          "attributes": [],
          "description": "Delete the specified classification request"
        }
      ],
      "attributes": [],
      "path": "/:organization/harmonization/classifications"
    },
    {
      "type": "detail",
      "plural": "details",
      "operations": [
        {
          "method": "GET",
          "path": "/:organization/harmonization/details",
          "parameters": [
            {
              "name": "organization",
              "type": "string",
              "location": "Path",
              "required": true
            },
            {
              "name": "id",
              "type": "[string]",
              "location": "Query",
              "required": false,
              "maximum": 100
            },
            {
              "name": "number",
              "type": "[string]",
              "location": "Query",
              "required": false,
              "maximum": 100
            },
            {
              "name": "status",
              "type": "status",
              "location": "Query",
              "required": false
            },
            {
              "name": "limit",
              "type": "long",
              "location": "Query",
              "required": true,
              "default": "25",
              "minimum": 1,
              "maximum": 100
            },
            {
              "name": "offset",
              "type": "long",
              "location": "Query",
              "required": true,
              "default": "0",
              "minimum": 0
            },
            {
              "name": "sort",
              "type": "string",
              "location": "Query",
              "required": true,
              "default": "-created_at"
            },
            {
              "name": "expand",
              "type": "[string]",
              "location": "Query",
              "required": false,
              "minimum": 0,
              "maximum": 1,
              "example": "classification"
            }
          ],
          "responses": [
            {
              "code": {
                "integer": {
                  "value": 200
                }
              },
              "type": "[detail]"
            },
            {
              "code": {
                "integer": {
                  "value": 401
                }
              },
              "type": "unit"
            }
          ],
          "attributes": [],
          "description": "Search details classification requests. Always paginated."
        },
        {
          "method": "GET",
          "path": "/:organization/harmonization/details/:id",
          "parameters": [
            {
              "name": "organization",
              "type": "string",
              "location": "Path",
              "required": true
            },
            {
              "name": "id",
              "type": "string",
              "location": "Path",
              "required": true
            },
            {
              "name": "expand",
              "type": "[string]",
              "location": "Query",
              "required": false,
              "minimum": 0,
              "maximum": 1,
              "example": "classification"
            }
          ],
          "responses": [
            {
              "code": {
                "integer": {
                  "value": 200
                }
              },
              "type": "detail"
            },
            {
              "code": {
                "integer": {
                  "value": 401
                }
              },
              "type": "unit"
            },
            {
              "code": {
                "integer": {
                  "value": 404
                }
              },
              "type": "unit"
            }
          ],
          "attributes": [],
          "description": "Returns information about a specific detail classification request."
        },
        {
          "method": "POST",
          "path": "/:organization/harmonization/details",
          "parameters": [
            {
              "name": "organization",
              "type": "string",
              "location": "Path",
              "required": true
            },
            {
              "name": "expand",
              "type": "[string]",
              "location": "Query",
              "required": false,
              "minimum": 0,
              "maximum": 1,
              "example": "classification"
            }
          ],
          "responses": [
            {
              "code": {
                "integer": {
                  "value": 201
                }
              },
              "type": "detail"
            },
            {
              "code": {
                "integer": {
                  "value": 401
                }
              },
              "type": "unit"
            },
            {
              "code": {
                "integer": {
                  "value": 422
                }
              },
              "type": "[io.flow.common.v0.models.error]"
            }
          ],
          "attributes": [],
          "description": "Create a detail classification request, which will be processed asynchronously. You can check for results by querying with GET using the id provided in the response.",
          "body": {
            "type": "detail_form",
            "attributes": []
          }
        },
        {
          "method": "DELETE",
          "path": "/:organization/harmonization/details/:id",
          "parameters": [
            {
              "name": "organization",
              "type": "string",
              "location": "Path",
              "required": true
            },
            {
              "name": "id",
              "type": "string",
              "location": "Path",
              "required": true
            }
          ],
          "responses": [
            {
              "code": {
                "integer": {
                  "value": 204
                }
              },
              "type": "unit"
            },
            {
              "code": {
                "integer": {
                  "value": 401
                }
              },
              "type": "unit"
            },
            {
              "code": {
                "integer": {
                  "value": 404
                }
              },
              "type": "unit"
            }
          ],
          "attributes": [],
          "description": "Delete the specified detail classification request"
        }
      ],
      "attributes": [],
      "path": "/:organization/harmonization/details"
    },
    {
      "type": "lane",
      "plural": "lanes",
      "operations": [
        {
          "method": "GET",
          "path": "/:organization/harmonization/lanes",
          "parameters": [
            {
              "name": "organization",
              "type": "string",
              "location": "Path",
              "required": true
            },
            {
              "name": "id",
              "type": "[string]",
              "location": "Query",
              "required": false,
              "maximum": 100
            },
            {
              "name": "country_of_origin",
              "type": "string",
              "location": "Query",
              "required": false,
              "description": "The ISO-3166 2 or 3 character country code of the destination country"
            },
            {
              "name": "destination",
              "type": "string",
              "location": "Query",
              "required": false,
              "description": "The ISO-3166 2 or 3 character country code of the destination country"
            },
            {
              "name": "limit",
              "type": "long",
              "location": "Query",
              "required": true,
              "default": "25",
              "minimum": 1,
              "maximum": 100
            },
            {
              "name": "offset",
              "type": "long",
              "location": "Query",
              "required": true,
              "default": "0",
              "minimum": 0
            },
            {
              "name": "sort",
              "type": "string",
              "location": "Query",
              "required": true,
              "default": "-created_at"
            }
          ],
          "responses": [
            {
              "code": {
                "integer": {
                  "value": 200
                }
              },
              "type": "[lane]"
            },
            {
              "code": {
                "integer": {
                  "value": 401
                }
              },
              "type": "unit"
            },
            {
              "code": {
                "integer": {
                  "value": 422
                }
              },
              "type": "[io.flow.common.v0.models.error]"
            }
          ],
          "attributes": [],
          "description": "Search lanes. Always paginated."
        },
        {
          "method": "GET",
          "path": "/:organization/harmonization/lanes/:id",
          "parameters": [
            {
              "name": "organization",
              "type": "string",
              "location": "Path",
              "required": true
            },
            {
              "name": "id",
              "type": "string",
              "location": "Path",
              "required": true
            }
          ],
          "responses": [
            {
              "code": {
                "integer": {
                  "value": 200
                }
              },
              "type": "lane"
            },
            {
              "code": {
                "integer": {
                  "value": 401
                }
              },
              "type": "unit"
            },
            {
              "code": {
                "integer": {
                  "value": 404
                }
              },
              "type": "unit"
            }
          ],
          "attributes": [],
          "description": "Returns information about a specific lane."
        },
        {
          "method": "POST",
          "path": "/:organization/harmonization/lanes",
          "parameters": [
            {
              "name": "organization",
              "type": "string",
              "location": "Path",
              "required": true
            }
          ],
          "responses": [
            {
              "code": {
                "integer": {
                  "value": 201
                }
              },
              "type": "lane"
            },
            {
              "code": {
                "integer": {
                  "value": 401
                }
              },
              "type": "unit"
            },
            {
              "code": {
                "integer": {
                  "value": 422
                }
              },
              "type": "[io.flow.common.v0.models.error]"
            }
          ],
          "attributes": [],
          "body": {
            "type": "lane_form",
            "attributes": []
          }
        },
        {
          "method": "DELETE",
          "path": "/:organization/harmonization/lanes/:id",
          "parameters": [
            {
              "name": "organization",
              "type": "string",
              "location": "Path",
              "required": true
            },
            {
              "name": "id",
              "type": "string",
              "location": "Path",
              "required": true
            }
          ],
          "responses": [
            {
              "code": {
                "integer": {
                  "value": 204
                }
              },
              "type": "unit"
            },
            {
              "code": {
                "integer": {
                  "value": 401
                }
              },
              "type": "unit"
            },
            {
              "code": {
                "integer": {
                  "value": 404
                }
              },
              "type": "unit"
            }
          ],
          "attributes": [],
          "description": "Delete the specified lane"
        }
      ],
      "attributes": [],
      "path": "/:organization/harmonization/lanes"
    }
  ],
  "attributes": []
}